pdfss/__init__.py
pdfss/py.typed
pdfss-3.0.1.dist-info/METADATA
pdfss-3.0.1.dist-info/WHEEL
pdfss-3.0.1.dist-info/licenses/COPYING
pdfss-3.0.1.dist-info/RECORD
