Metadata-Version: 2.4
Name: pdfss
Version: 3.0.1
Summary: PDF scraping system
Project-URL: Source, https://github.com/lowatt/pdfss
Project-URL: Tracker, https://github.com/lowatt/pdfss/issues
Author-email: Lowatt <info@lowatt.fr>
License: GPLv3
License-File: COPYING
Classifier: Development Status :: 5 - Production/Stable
Classifier: License :: OSI Approved :: GNU General Public License v3 or later (GPLv3+)
Classifier: Operating System :: OS Independent
Classifier: Programming Language :: Python :: 3
Classifier: Programming Language :: Python :: 3 :: Only
Classifier: Programming Language :: Python :: 3.9
Classifier: Programming Language :: Python :: 3.10
Classifier: Programming Language :: Python :: 3.11
Classifier: Programming Language :: Python :: 3.12
Classifier: Programming Language :: Python :: 3.13
Classifier: Typing :: Typed
Requires-Python: >=3.9
Requires-Dist: pdfminer-six
Requires-Dist: typing-extensions
Provides-Extra: test
Requires-Dist: pytest; extra == 'test'
Requires-Dist: pytest-cov; extra == 'test'
Provides-Extra: typing
Requires-Dist: mypy; extra == 'typing'
